{
  "channelId": "UCHIFSavpHG0kGXNlZrrMVwQ",
  "fetchedAt": "2026-03-28T21:57:13.999Z",
  "channelTitle": "Oscar Lindhardt",
  "items": [
    {
      "title": "I spent a week trying to buy business in UK (running Private Equity firm from scratch)",
      "published": "2026-03-08T17:01:18+00:00",
      "videoId": "rx-l1VtIksc",
      "link": "https://www.youtube.com/watch?v=rx-l1VtIksc",
      "thumbnail": "https://i3.ytimg.com/vi/rx-l1VtIksc/hqdefault.jpg"
    },
    {
      "title": "I Run Private Equity firm SOLO (private equity entrepreneur | business growth / investing &amp; more)",
      "published": "2026-02-15T18:00:35+00:00",
      "videoId": "Rc-eLabpE3c",
      "link": "https://www.youtube.com/watch?v=Rc-eLabpE3c",
      "thumbnail": "https://i3.ytimg.com/vi/Rc-eLabpE3c/hqdefault.jpg"
    },
    {
      "title": "I chased my dream of starting a private equity firm… this is how to break in.",
      "published": "2026-01-25T16:30:17+00:00",
      "videoId": "i4GOSZUVUzc",
      "link": "https://www.youtube.com/watch?v=i4GOSZUVUzc",
      "thumbnail": "https://i2.ytimg.com/vi/i4GOSZUVUzc/hqdefault.jpg"
    },
    {
      "title": "How I Run Private Equity firm SOLO (step by step / from scratch / without being rich)",
      "published": "2026-01-06T15:36:40+00:00",
      "videoId": "yAKoy3vDjdo",
      "link": "https://www.youtube.com/watch?v=yAKoy3vDjdo",
      "thumbnail": "https://i2.ytimg.com/vi/yAKoy3vDjdo/hqdefault.jpg"
    },
    {
      "title": "I went to London to raise money for the firm…",
      "published": "2025-12-08T20:12:57+00:00",
      "videoId": "r6UuPwZssgY",
      "link": "https://www.youtube.com/watch?v=r6UuPwZssgY",
      "thumbnail": "https://i3.ytimg.com/vi/r6UuPwZssgY/hqdefault.jpg"
    },
    {
      "title": "Attempting BUYOUT of A $216K/Month Business without A finance degree",
      "published": "2025-11-16T14:30:19+00:00",
      "videoId": "QjPwPiIA1AM",
      "link": "https://www.youtube.com/watch?v=QjPwPiIA1AM",
      "thumbnail": "https://i2.ytimg.com/vi/QjPwPiIA1AM/hqdefault.jpg"
    },
    {
      "title": "I started a private equity firm in my 20s... am I cheating?",
      "published": "2025-10-29T15:01:40+00:00",
      "videoId": "pAsglueli7g",
      "link": "https://www.youtube.com/watch?v=pAsglueli7g",
      "thumbnail": "https://i1.ytimg.com/vi/pAsglueli7g/hqdefault.jpg"
    },
    {
      "title": "the real life of private equity in London..",
      "published": "2025-10-15T13:54:29+00:00",
      "videoId": "ZoQ4DZIyuKI",
      "link": "https://www.youtube.com/watch?v=ZoQ4DZIyuKI",
      "thumbnail": "https://i3.ytimg.com/vi/ZoQ4DZIyuKI/hqdefault.jpg"
    },
    {
      "title": "I burned out starting a private equity firm.",
      "published": "2025-09-28T07:00:07+00:00",
      "videoId": "8-Rbbg2X2jo",
      "link": "https://www.youtube.com/watch?v=8-Rbbg2X2jo",
      "thumbnail": "https://i1.ytimg.com/vi/8-Rbbg2X2jo/hqdefault.jpg"
    },
    {
      "title": "I started a private equity firm from nothing...",
      "published": "2025-09-14T07:30:32+00:00",
      "videoId": "fYnerEjjEq8",
      "link": "https://www.youtube.com/watch?v=fYnerEjjEq8",
      "thumbnail": "https://i3.ytimg.com/vi/fYnerEjjEq8/hqdefault.jpg"
    },
    {
      "title": "I dropped everything on private equity.",
      "published": "2025-08-31T07:30:21+00:00",
      "videoId": "BxV1I4PJgq0",
      "link": "https://www.youtube.com/watch?v=BxV1I4PJgq0",
      "thumbnail": "https://i3.ytimg.com/vi/BxV1I4PJgq0/hqdefault.jpg"
    },
    {
      "title": "28 y/o entrepreneur starts private equity firm in London",
      "published": "2025-08-17T07:00:27+00:00",
      "videoId": "Z7VNKoc7zq8",
      "link": "https://www.youtube.com/watch?v=Z7VNKoc7zq8",
      "thumbnail": "https://i3.ytimg.com/vi/Z7VNKoc7zq8/hqdefault.jpg"
    }
  ]
}